freud/__init__.py
freud/_box.abi3.so
freud/_cluster.abi3.so
freud/_density.abi3.so
freud/_diffraction.abi3.so
freud/_environment.abi3.so
freud/_locality.abi3.so
freud/_order.abi3.so
freud/_parallel.abi3.so
freud/_pmft.abi3.so
freud/_util.abi3.so
freud/box.py
freud/cluster.py
freud/data.py
freud/density.py
freud/diffraction.py
freud/environment.py
freud/errors.py
freud/interface.py
freud/locality.py
freud/msd.py
freud/order.py
freud/parallel.py
freud/plot.py
freud/pmft.py
freud/util.py
freud_analysis.libs/libtbb-52d31ba0.so.12.15
freud_analysis-3.5.0.dist-info/METADATA
freud_analysis-3.5.0.dist-info/WHEEL
freud_analysis-3.5.0.dist-info/RECORD
freud_analysis-3.5.0.dist-info/licenses/LICENSE
