Metadata-Version: 2.4
Name: freud-analysis
Version: 3.5.0
Summary: Powerful, efficient trajectory analysis in scientific Python.
Keywords: simulation,analysis,molecular dynamics,soft matter,particle,system,computational,physics
Author: The Glotzer Lab
Maintainer: freud Developers
License-Expression: BSD-3-Clause
License-File: LICENSE
Classifier: Development Status :: 5 - Production/Stable
Classifier: Intended Audience :: Science/Research
Classifier: Topic :: Scientific/Engineering :: Chemistry
Classifier: Topic :: Scientific/Engineering :: Physics
Classifier: Programming Language :: C++
Classifier: Programming Language :: Cython
Classifier: Programming Language :: Python :: 3.9
Classifier: Programming Language :: Python :: 3.10
Classifier: Programming Language :: Python :: 3.11
Classifier: Programming Language :: Python :: 3.12
Classifier: Programming Language :: Python :: 3.13
Project-URL: Documentation, https://freud.readthedocs.io
Project-URL: Download, https://pypi.org/project/freud-analysis/
Project-URL: Source, https://github.com/glotzerlab/freud
Project-URL: Issues, https://github.com/glotzerlab/freud/issues
Requires-Python: >=3.12
Requires-Dist: numpy>=1.19
Requires-Dist: rowan>=1.2.1
Requires-Dist: scipy>=1.1
Requires-Dist: parsnip-cif>=0.2.0
